[
    {
        "name": "Landeshauptstadt Dresden", 
        "y": 53.4
    }, 
    {
        "name": "Stadt Leipzig", 
        "y": 32.5
    }, 
    {
        "name": "Stadt Chemnitz", 
        "y": 28.6
    }, 
    {
        "name": "Landkreis Bautzen", 
        "y": 55.4
    }, 
    {
        "name": "Erzgebirgskreis", 
        "y": 77.7
    }, 
    {
        "name": "Landkreis G\u00f6rlitz", 
        "y": 47.1
    }, 
    {
        "name": "Landkreis Leipzig", 
        "y": 45.3
    }, 
    {
        "name": "Landkreis Mei\u00dfen", 
        "y": 42.0
    }, 
    {
        "name": "Landkreis Mittelsachsen", 
        "y": 60.7
    }, 
    {
        "name": "Landkreis Nordsachsen", 
        "y": 20.8
    }, 
    {
        "name": "Landkreis S\u00e4chsische Schweiz-Osterzgebirge", 
        "y": 48.6
    }, 
    {
        "name": "Vogtlandkreis", 
        "y": 34.8
    }, 
    {
        "name": "Landkreis Zwickau", 
        "y": 31.1
    }, 
    {
        "name": "Sachsen gesamt", 
        "y": 45.3
    }
]
